compmec/section/__init__.py
compmec/section/abcs.py
compmec/section/curve.py
compmec/section/dataio.py
compmec/section/field.py
compmec/section/geometry.py
compmec/section/integral.py
compmec/section/material.py
compmec/section/schema/curve.json
compmec/section/schema/material.json
compmec/section/schema/section.json
compmec/section/section.py
compmec_section-0.4.0.dist-info/LICENSE.md
compmec_section-0.4.0.dist-info/METADATA
compmec_section-0.4.0.dist-info/WHEEL
compmec_section-0.4.0.dist-info/RECORD
