Metadata-Version: 2.1
Name: compmec-section
Version: 0.4.0
Summary: Analysis of beams cross-section using the boundary element method
Author: Carlos Adir
Author-email: carlos.adir.leite@gmail.com
Requires-Python: >=3.7,<4.0
Classifier: Programming Language :: Python :: 3
Classifier: Programming Language :: Python :: 3.7
Classifier: Programming Language :: Python :: 3.8
Classifier: Programming Language :: Python :: 3.9
Classifier: Programming Language :: Python :: 3.10
Classifier: Programming Language :: Python :: 3.11
Classifier: Programming Language :: Python :: 3.12
Requires-Dist: compmec-nurbs (>=1.0.0,<2.0.0)
Requires-Dist: compmec-shape (>=1.0.0,<2.0.0)
Requires-Dist: jsonschema (>=4.17.3,<5.0.0)
Requires-Dist: numpy (>=1.0.0,<2.0.0)
